gem/__init__.py
gem/version.py
gem/c_exe/node2vec
gem/c_exe/readme.txt
gem/c_ext/__init__.py
gem/c_src/Jamfile
gem/c_src/Jamfile_backup
gem/c_src/bjamCall.txt
gem/c_src/gf.cpp
gem/c_src/graphFac.cpp
gem/c_src/graphFac_blas.cpp
gem/c_src/graphFac_ret_ndarray.cpp
gem/embedding/__init__.py
gem/embedding/gf.py
gem/embedding/hope.py
gem/embedding/lap.py
gem/embedding/lle.py
gem/embedding/node2vec.py
gem/embedding/sdne.py
gem/embedding/sdne_utils.py
gem/embedding/static_graph_embedding.py
gem/evaluation/__init__.py
gem/evaluation/evaluate_graph_reconstruction.py
gem/evaluation/metrics.py
gem/evaluation/visualize_embedding.py
gem/utils/__init__.py
gem/utils/evaluation_util.py
gem/utils/graph_util.py
gem/utils/plot_util.py
nxt_gem-2.0.3.dist-info/AUTHORS
nxt_gem-2.0.3.dist-info/LICENSE
nxt_gem-2.0.3.dist-info/METADATA
nxt_gem-2.0.3.dist-info/WHEEL
nxt_gem-2.0.3.dist-info/pbr.json
nxt_gem-2.0.3.dist-info/top_level.txt
nxt_gem-2.0.3.dist-info/RECORD
