Metadata-Version: 2.1
Name: nxt-gem
Version: 2.0.3
Summary: nxt_gem: A Python module for Graph Embedding Methods
Home-page: https://github.com/jernsting/nxt_gem
Download-URL: https://pypi.org/project/nxt_gem/#files
Author: Jan Ernsting
Author-email: j.ernsting@uni-muenster.de
License: BSD
Project-URL: Source Code, https://github.com/jernsting/nxt_gem
Project-URL: Bug Tracker, https://github.com/jernsting/nxt_gem/issues
Keywords: graph embedding,network analysis,network embedding,data mining,machine learning
Classifier: License :: OSI Approved :: MIT License
Classifier: Topic :: Software Development :: Libraries :: Python Modules
Classifier: Topic :: Scientific/Engineering :: Artificial Intelligence
Classifier: Intended Audience :: Science/Research
License-File: LICENSE
License-File: AUTHORS
Requires-Dist: numpy (==1.24.2)
Requires-Dist: scipy (>=0.19.0)
Requires-Dist: networkx (==3.0)
Requires-Dist: matplotlib (>=2.0.0)
Requires-Dist: scikit-learn (>=0.21.2)
Requires-Dist: theano (>=0.9.0)
Requires-Dist: tensorflow (==2.11)
Requires-Dist: pbr
